alexisomggeneratelatextable/__init__.py
alexisomggeneratelatextable/task1.py
alexisomggeneratelatextable-0.0.2.dist-info/METADATA
alexisomggeneratelatextable-0.0.2.dist-info/WHEEL
alexisomggeneratelatextable-0.0.2.dist-info/top_level.txt
alexisomggeneratelatextable-0.0.2.dist-info/RECORD
