Metadata-Version: 2.1
Name: alexisomggeneratelatextable
Version: 0.0.2
Summary: ДЗ по Python 
Home-page: UNKNOWN
Author: AlexisOMG
Author-email: alesha-gramazeka@yandex.ru
License: UNKNOWN
Project-URL: GitHub, https://github.com/AlexisOMG/mhs-python
Platform: UNKNOWN
Requires-Python: >=3.8
